LICENSE
README.md
setup.py
imantics_lts/__init__.py
imantics_lts/annotation.py
imantics_lts/basic.py
imantics_lts/category.py
imantics_lts/color.py
imantics_lts/dataset.py
imantics_lts/image.py
imantics_lts/point.py
imantics_lts/styles.py
imantics_lts/utils.py
imantics_lts.egg-info/PKG-INFO
imantics_lts.egg-info/SOURCES.txt
imantics_lts.egg-info/dependency_links.txt
imantics_lts.egg-info/not-zip-safe
imantics_lts.egg-info/requires.txt
imantics_lts.egg-info/top_level.txt